LICENSE.txt
MANIFEST.in
README.rst
VERSION
setup.py
pretendsmtp/__init__.py
pretendsmtp/commandline.py
pretendsmtp/email.jinja2
pretendsmtp/mock_server.py
pretendsmtp.egg-info/PKG-INFO
pretendsmtp.egg-info/SOURCES.txt
pretendsmtp.egg-info/dependency_links.txt
pretendsmtp.egg-info/entry_points.txt
pretendsmtp.egg-info/not-zip-safe
pretendsmtp.egg-info/requires.txt
pretendsmtp.egg-info/top_level.txt
pretendsmtp/include/bootstrap-3.3.7.min.css